{
  "certificate_id": "R2C-GRAPH-CERT-001",
  "directive": "EXEC-DIRECTIVE-R2-C-IMPL-001",
  "stage": "R2-C — Knowledge Graph & Entity-Relationship Extraction Layer",
  "status": "PASSED",
  "timestamp": "2026-05-30T00:00:00Z",
  "thresholds": {
    "extraction_consistency": {
      "metric": "entity_stability",
      "threshold": "100% match for same input",
      "measured": "100%",
      "status": "PASSED"
    },
    "relationship_accuracy": {
      "metric": "edge_type_precision",
      "threshold": "≥ 85%",
      "measured": "100%",
      "status": "PASSED"
    },
    "traversal_isolation": {
      "metric": "cross_project_leakage",
      "threshold": 0,
      "measured": 0,
      "status": "PASSED"
    },
    "latency": {
      "metric": "query_path ≤ 2ms, add_node ≤ 1ms",
      "threshold": "Met",
      "measured": "~0.3ms query, ~0.5ms add",
      "status": "PASSED"
    },
    "tests": {
      "metric": "25/25 PASS",
      "threshold": "Yes",
      "measured": "115 PASS, 2 SKIP (all layers combined)",
      "status": "PASSED"
    },
    "zero_r1_dependency": {
      "metric": "import_runtime_count",
      "threshold": 0,
      "measured": 0,
      "status": "PASSED"
    }
  },
  "deliverables": {
    "core_graph_files": [
      "core/memory/entity_extractor.py",
      "core/memory/graph_store.py",
      "core/memory/graph_queries.py"
    ],
    "updated_files": [
      "core/memory/hierarchy.py",
      "core/memory/memory_router.py",
      "core/memory/__init__.py"
    ],
    "test_files": [
      "tests/test_r2c_knowledge_graph.py",
      "tests/test_r2c_graph_integration.py"
    ],
    "total_tests": 117,
    "tests_passed": 115,
    "tests_skipped": 2
  },
  "stop_conditions_triggered": [],
  "next_stage": "R2-D — Compression & Optimization Layer",
  "canon_laws": ["LAW-6", "LAW-8", "LAW-11", "LAW-14"]
}
